listenclosely_telegram/__init__.py
listenclosely_telegram/bot.py
listenclosely_telegram/conf.py
listenclosely_telegram/service.py
listenclosely_telegram-0.1.0.dist-info/DESCRIPTION.rst
listenclosely_telegram-0.1.0.dist-info/METADATA
listenclosely_telegram-0.1.0.dist-info/RECORD
listenclosely_telegram-0.1.0.dist-info/WHEEL
listenclosely_telegram-0.1.0.dist-info/metadata.json
listenclosely_telegram-0.1.0.dist-info/top_level.txt
