Metadata-Version: 2.0
Name: listenclosely-telegram
Version: 0.1.0
Summary: ListenClosely service backenTelegram
Home-page: https://github.com/jlmadurga/listenclosely-telegram
Author: Juan Madurga
Author-email: jlmadurga@gmail.com
License: ISCL
Keywords: listenclosely-telegram
Platform: UNKNOWN
Classifier: Development Status :: 2 - Pre-Alpha
Classifier: Intended Audience :: Developers
Classifier: License :: OSI Approved :: ISC License (ISCL)
Classifier: Natural Language :: English
Classifier: Programming Language :: Python :: 2
Classifier: Programming Language :: Python :: 2.7
Classifier: Programming Language :: Python :: 3
Classifier: Programming Language :: Python :: 3.4
Classifier: Programming Language :: Python :: 3.5
Requires-Dist: listenclosely (==0.1.0)
Requires-Dist: twx.botapi (==2.0.1)
